{
  "baseline": {
    "csv": "C:\\Users\\sawaiz\\Desktop\\superMario64-TAS\\logs\\run_us_20260722_135407.csv",
    "rows": 342,
    "reached_star": true,
    "star_touch_sample": 225,
    "star_touch_vi": 540,
    "star_touch_action": 6404,
    "star_exit_sample": 228,
    "star_exit_vi": 546,
    "star_sample": 228,
    "star_vi": 546,
    "star_global_timer": 2361,
    "end_action": 4866,
    "end_x": -1931.085449,
    "end_y": -2518.0,
    "end_z": -2926.145264,
    "first_walking_sample": 101,
    "first_walking_vi": 292,
    "first_jump_sample": 135,
    "first_jump_vi": 360,
    "first_jump_kick_sample": 106,
    "first_jump_kick_vi": 302,
    "parity_hash": "8417f43b9b1bd710",
    "parity_checkpoints": 34
  },
  "seed": {
    "csv": "C:\\Users\\sawaiz\\Desktop\\superMario64-TAS\\logs\\run_us_20260722_135412.csv",
    "rows": 342,
    "reached_star": true,
    "star_touch_sample": 224,
    "star_touch_vi": 538,
    "star_touch_action": 6404,
    "star_exit_sample": 228,
    "star_exit_vi": 546,
    "star_sample": 228,
    "star_vi": 546,
    "star_global_timer": 2360,
    "end_action": 4866,
    "end_x": -1976.03186,
    "end_y": -2518.0,
    "end_z": -2897.080078,
    "first_walking_sample": 101,
    "first_walking_vi": 292,
    "first_jump_sample": 135,
    "first_jump_vi": 360,
    "first_jump_kick_sample": 106,
    "first_jump_kick_vi": 302,
    "parity_hash": "ce4ac67839bde3b9",
    "parity_checkpoints": 34
  },
  "candidates": [
    {
      "candidate": "window_start_136",
      "edit_count": 66,
      "csv": "C:\\Users\\sawaiz\\Desktop\\superMario64-TAS\\logs\\run_us_20260722_135417.csv",
      "rows": 342,
      "reached_star": false,
      "star_touch_sample": null,
      "star_touch_vi": null,
      "star_touch_action": null,
      "star_exit_sample": null,
      "star_exit_vi": null,
      "star_sample": null,
      "star_vi": null,
      "star_global_timer": null,
      "end_action": 67109952,
      "end_x": -2136.401123,
      "end_y": 2563.928223,
      "end_z": -1602.703125,
      "first_walking_sample": 101,
      "first_walking_vi": 292,
      "first_jump_sample": 135,
      "first_jump_vi": 360,
      "first_jump_kick_sample": 106,
      "first_jump_kick_vi": 302,
      "parity_hash": "049071c2ca441e7d",
      "parity_checkpoints": 34,
      "result": "rejected: star not reached"
    },
    {
      "candidate": "window_start_137",
      "edit_count": 65,
      "csv": "C:\\Users\\sawaiz\\Desktop\\superMario64-TAS\\logs\\run_us_20260722_135421.csv",
      "rows": 342,
      "reached_star": false,
      "star_touch_sample": null,
      "star_touch_vi": null,
      "star_touch_action": null,
      "star_exit_sample": null,
      "star_exit_vi": null,
      "star_sample": null,
      "star_vi": null,
      "star_global_timer": null,
      "end_action": 67109952,
      "end_x": -2150.626465,
      "end_y": 2571.68335,
      "end_z": -1594.145874,
      "first_walking_sample": 101,
      "first_walking_vi": 292,
      "first_jump_sample": 135,
      "first_jump_vi": 360,
      "first_jump_kick_sample": 106,
      "first_jump_kick_vi": 302,
      "parity_hash": "64810b0965b4319f",
      "parity_checkpoints": 34,
      "result": "rejected: star not reached"
    },
    {
      "candidate": "window_start_138",
      "edit_count": 64,
      "csv": "C:\\Users\\sawaiz\\Desktop\\superMario64-TAS\\logs\\run_us_20260722_135426.csv",
      "rows": 342,
      "reached_star": false,
      "star_touch_sample": null,
      "star_touch_vi": null,
      "star_touch_action": null,
      "star_exit_sample": null,
      "star_exit_vi": null,
      "star_sample": null,
      "star_vi": null,
      "star_global_timer": null,
      "end_action": 67109952,
      "end_x": -2140.061523,
      "end_y": 2565.56958,
      "end_z": -1601.782104,
      "first_walking_sample": 101,
      "first_walking_vi": 292,
      "first_jump_sample": 135,
      "first_jump_vi": 360,
      "first_jump_kick_sample": 106,
      "first_jump_kick_vi": 302,
      "parity_hash": "1e1df46703cf5558",
      "parity_checkpoints": 34,
      "result": "rejected: star not reached"
    },
    {
      "candidate": "window_start_139",
      "edit_count": 63,
      "csv": "C:\\Users\\sawaiz\\Desktop\\superMario64-TAS\\logs\\run_us_20260722_135431.csv",
      "rows": 342,
      "reached_star": false,
      "star_touch_sample": null,
      "star_touch_vi": null,
      "star_touch_action": null,
      "star_exit_sample": null,
      "star_exit_vi": null,
      "star_sample": null,
      "star_vi": null,
      "star_global_timer": null,
      "end_action": 67109952,
      "end_x": -2135.687256,
      "end_y": 2563.629883,
      "end_z": -1602.231445,
      "first_walking_sample": 101,
      "first_walking_vi": 292,
      "first_jump_sample": 135,
      "first_jump_vi": 360,
      "first_jump_kick_sample": 106,
      "first_jump_kick_vi": 302,
      "parity_hash": "4a53ea2b8e0e8565",
      "parity_checkpoints": 34,
      "result": "rejected: star not reached"
    },
    {
      "candidate": "window_start_140",
      "edit_count": 62,
      "csv": "C:\\Users\\sawaiz\\Desktop\\superMario64-TAS\\logs\\run_us_20260722_135435.csv",
      "rows": 342,
      "reached_star": false,
      "star_touch_sample": null,
      "star_touch_vi": null,
      "star_touch_action": null,
      "star_exit_sample": null,
      "star_exit_vi": null,
      "star_sample": null,
      "star_vi": null,
      "star_global_timer": null,
      "end_action": 67109952,
      "end_x": -2130.067871,
      "end_y": 2560.0,
      "end_z": -1609.239624,
      "first_walking_sample": 101,
      "first_walking_vi": 292,
      "first_jump_sample": 135,
      "first_jump_vi": 360,
      "first_jump_kick_sample": 106,
      "first_jump_kick_vi": 302,
      "parity_hash": "ca8438a31ba22fa0",
      "parity_checkpoints": 34,
      "result": "rejected: star not reached"
    },
    {
      "candidate": "window_start_141",
      "edit_count": 61,
      "csv": "C:\\Users\\sawaiz\\Desktop\\superMario64-TAS\\logs\\run_us_20260722_135439.csv",
      "rows": 342,
      "reached_star": false,
      "star_touch_sample": null,
      "star_touch_vi": null,
      "star_touch_action": null,
      "star_exit_sample": null,
      "star_exit_vi": null,
      "star_sample": null,
      "star_vi": null,
      "star_global_timer": null,
      "end_action": 67109952,
      "end_x": -2115.503174,
      "end_y": 2560.0,
      "end_z": -1616.313477,
      "first_walking_sample": 101,
      "first_walking_vi": 292,
      "first_jump_sample": 135,
      "first_jump_vi": 360,
      "first_jump_kick_sample": 106,
      "first_jump_kick_vi": 302,
      "parity_hash": "3a1ba793e446fc31",
      "parity_checkpoints": 34,
      "result": "rejected: star not reached"
    },
    {
      "candidate": "window_start_142",
      "edit_count": 60,
      "csv": "C:\\Users\\sawaiz\\Desktop\\superMario64-TAS\\logs\\run_us_20260722_135444.csv",
      "rows": 342,
      "reached_star": false,
      "star_touch_sample": null,
      "star_touch_vi": null,
      "star_touch_action": null,
      "star_exit_sample": null,
      "star_exit_vi": null,
      "star_sample": null,
      "star_vi": null,
      "star_global_timer": null,
      "end_action": 67109952,
      "end_x": -2104.802734,
      "end_y": 2560.0,
      "end_z": -1619.668213,
      "first_walking_sample": 101,
      "first_walking_vi": 292,
      "first_jump_sample": 135,
      "first_jump_vi": 360,
      "first_jump_kick_sample": 106,
      "first_jump_kick_vi": 302,
      "parity_hash": "0ee21953e10be9ab",
      "parity_checkpoints": 34,
      "result": "rejected: star not reached"
    },
    {
      "candidate": "window_start_143",
      "edit_count": 59,
      "csv": "C:\\Users\\sawaiz\\Desktop\\superMario64-TAS\\logs\\run_us_20260722_135449.csv",
      "rows": 342,
      "reached_star": false,
      "star_touch_sample": null,
      "star_touch_vi": null,
      "star_touch_action": null,
      "star_exit_sample": null,
      "star_exit_vi": null,
      "star_sample": null,
      "star_vi": null,
      "star_global_timer": null,
      "end_action": 67109952,
      "end_x": -2104.42334,
      "end_y": 2560.0,
      "end_z": -1619.889038,
      "first_walking_sample": 101,
      "first_walking_vi": 292,
      "first_jump_sample": 135,
      "first_jump_vi": 360,
      "first_jump_kick_sample": 106,
      "first_jump_kick_vi": 302,
      "parity_hash": "34ea89713a1afc49",
      "parity_checkpoints": 34,
      "result": "rejected: star not reached"
    },
    {
      "candidate": "window_start_144",
      "edit_count": 58,
      "csv": "C:\\Users\\sawaiz\\Desktop\\superMario64-TAS\\logs\\run_us_20260722_135453.csv",
      "rows": 342,
      "reached_star": false,
      "star_touch_sample": null,
      "star_touch_vi": null,
      "star_touch_action": null,
      "star_exit_sample": null,
      "star_exit_vi": null,
      "star_sample": null,
      "star_vi": null,
      "star_global_timer": null,
      "end_action": 67109952,
      "end_x": -2095.009521,
      "end_y": 2560.0,
      "end_z": -1623.662842,
      "first_walking_sample": 101,
      "first_walking_vi": 292,
      "first_jump_sample": 135,
      "first_jump_vi": 360,
      "first_jump_kick_sample": 106,
      "first_jump_kick_vi": 302,
      "parity_hash": "9dc2878854ef2029",
      "parity_checkpoints": 34,
      "result": "rejected: star not reached"
    },
    {
      "candidate": "window_start_145",
      "edit_count": 57,
      "csv": "C:\\Users\\sawaiz\\Desktop\\superMario64-TAS\\logs\\run_us_20260722_135458.csv",
      "rows": 342,
      "reached_star": false,
      "star_touch_sample": null,
      "star_touch_vi": null,
      "star_touch_action": null,
      "star_exit_sample": null,
      "star_exit_vi": null,
      "star_sample": null,
      "star_vi": null,
      "star_global_timer": null,
      "end_action": 67109952,
      "end_x": -2095.07666,
      "end_y": 2560.0,
      "end_z": -1623.393555,
      "first_walking_sample": 101,
      "first_walking_vi": 292,
      "first_jump_sample": 135,
      "first_jump_vi": 360,
      "first_jump_kick_sample": 106,
      "first_jump_kick_vi": 302,
      "parity_hash": "34be57667c25442b",
      "parity_checkpoints": 34,
      "result": "rejected: star not reached"
    },
    {
      "candidate": "window_start_146",
      "edit_count": 56,
      "csv": "C:\\Users\\sawaiz\\Desktop\\superMario64-TAS\\logs\\run_us_20260722_135503.csv",
      "rows": 342,
      "reached_star": false,
      "star_touch_sample": null,
      "star_touch_vi": null,
      "star_touch_action": null,
      "star_exit_sample": null,
      "star_exit_vi": null,
      "star_sample": null,
      "star_vi": null,
      "star_global_timer": null,
      "end_action": 67109952,
      "end_x": -2095.706543,
      "end_y": 2560.0,
      "end_z": -1623.833618,
      "first_walking_sample": 101,
      "first_walking_vi": 292,
      "first_jump_sample": 135,
      "first_jump_vi": 360,
      "first_jump_kick_sample": 106,
      "first_jump_kick_vi": 302,
      "parity_hash": "ca5be2c14b81a9a6",
      "parity_checkpoints": 34,
      "result": "rejected: star not reached"
    },
    {
      "candidate": "window_start_147",
      "edit_count": 55,
      "csv": "C:\\Users\\sawaiz\\Desktop\\superMario64-TAS\\logs\\run_us_20260722_135508.csv",
      "rows": 342,
      "reached_star": false,
      "star_touch_sample": null,
      "star_touch_vi": null,
      "star_touch_action": null,
      "star_exit_sample": null,
      "star_exit_vi": null,
      "star_sample": null,
      "star_vi": null,
      "star_global_timer": null,
      "end_action": 67109952,
      "end_x": -2095.911621,
      "end_y": 2560.0,
      "end_z": -1623.587158,
      "first_walking_sample": 101,
      "first_walking_vi": 292,
      "first_jump_sample": 135,
      "first_jump_vi": 360,
      "first_jump_kick_sample": 106,
      "first_jump_kick_vi": 302,
      "parity_hash": "58928bb75edab8ef",
      "parity_checkpoints": 34,
      "result": "rejected: star not reached"
    },
    {
      "candidate": "window_start_148",
      "edit_count": 54,
      "csv": "C:\\Users\\sawaiz\\Desktop\\superMario64-TAS\\logs\\run_us_20260722_135512.csv",
      "rows": 342,
      "reached_star": false,
      "star_touch_sample": null,
      "star_touch_vi": null,
      "star_touch_action": null,
      "star_exit_sample": null,
      "star_exit_vi": null,
      "star_sample": null,
      "star_vi": null,
      "star_global_timer": null,
      "end_action": 67109952,
      "end_x": -2095.035156,
      "end_y": 2560.0,
      "end_z": -1623.383179,
      "first_walking_sample": 101,
      "first_walking_vi": 292,
      "first_jump_sample": 135,
      "first_jump_vi": 360,
      "first_jump_kick_sample": 106,
      "first_jump_kick_vi": 302,
      "parity_hash": "40d174d185b1d49e",
      "parity_checkpoints": 34,
      "result": "rejected: star not reached"
    },
    {
      "candidate": "window_start_150",
      "edit_count": 52,
      "csv": "C:\\Users\\sawaiz\\Desktop\\superMario64-TAS\\logs\\run_us_20260722_135517.csv",
      "rows": 342,
      "reached_star": true,
      "star_touch_sample": 224,
      "star_touch_vi": 538,
      "star_touch_action": 6404,
      "star_exit_sample": 228,
      "star_exit_vi": 546,
      "star_sample": 228,
      "star_vi": 546,
      "star_global_timer": 2360,
      "end_action": 4866,
      "end_x": -1975.805786,
      "end_y": -2518.0,
      "end_z": -2897.087891,
      "first_walking_sample": 101,
      "first_walking_vi": 292,
      "first_jump_sample": 135,
      "first_jump_vi": 360,
      "first_jump_kick_sample": 106,
      "first_jump_kick_vi": 302,
      "parity_hash": "0a394c4ba6ffe94d",
      "parity_checkpoints": 34,
      "result": "ties verified seed"
    },
    {
      "candidate": "window_start_151",
      "edit_count": 51,
      "csv": "C:\\Users\\sawaiz\\Desktop\\superMario64-TAS\\logs\\run_us_20260722_135522.csv",
      "rows": 342,
      "reached_star": true,
      "star_touch_sample": 224,
      "star_touch_vi": 538,
      "star_touch_action": 6404,
      "star_exit_sample": 228,
      "star_exit_vi": 546,
      "star_sample": 228,
      "star_vi": 546,
      "star_global_timer": 2360,
      "end_action": 4866,
      "end_x": -1977.451538,
      "end_y": -2518.0,
      "end_z": -2888.345215,
      "first_walking_sample": 101,
      "first_walking_vi": 292,
      "first_jump_sample": 135,
      "first_jump_vi": 360,
      "first_jump_kick_sample": 106,
      "first_jump_kick_vi": 302,
      "parity_hash": "1905c2041243cef8",
      "parity_checkpoints": 34,
      "result": "ties verified seed"
    },
    {
      "candidate": "window_start_152",
      "edit_count": 50,
      "csv": "C:\\Users\\sawaiz\\Desktop\\superMario64-TAS\\logs\\run_us_20260722_135527.csv",
      "rows": 342,
      "reached_star": true,
      "star_touch_sample": 226,
      "star_touch_vi": 542,
      "star_touch_action": 6404,
      "star_exit_sample": 229,
      "star_exit_vi": 548,
      "star_sample": 229,
      "star_vi": 548,
      "star_global_timer": 2362,
      "end_action": 4866,
      "end_x": -1974.942017,
      "end_y": -2518.0,
      "end_z": -2888.505371,
      "first_walking_sample": 101,
      "first_walking_vi": 292,
      "first_jump_sample": 135,
      "first_jump_vi": 360,
      "first_jump_kick_sample": 106,
      "first_jump_kick_vi": 302,
      "parity_hash": "18684206783a3de2",
      "parity_checkpoints": 34,
      "result": "slower"
    },
    {
      "candidate": "window_start_153",
      "edit_count": 49,
      "csv": "C:\\Users\\sawaiz\\Desktop\\superMario64-TAS\\logs\\run_us_20260722_135531.csv",
      "rows": 342,
      "reached_star": true,
      "star_touch_sample": 224,
      "star_touch_vi": 538,
      "star_touch_action": 6404,
      "star_exit_sample": 228,
      "star_exit_vi": 546,
      "star_sample": 228,
      "star_vi": 546,
      "star_global_timer": 2360,
      "end_action": 4866,
      "end_x": -1974.728149,
      "end_y": -2518.0,
      "end_z": -2888.46582,
      "first_walking_sample": 101,
      "first_walking_vi": 292,
      "first_jump_sample": 135,
      "first_jump_vi": 360,
      "first_jump_kick_sample": 106,
      "first_jump_kick_vi": 302,
      "parity_hash": "69b9eb3fa039f0ac",
      "parity_checkpoints": 34,
      "result": "ties verified seed"
    },
    {
      "candidate": "window_start_154",
      "edit_count": 48,
      "csv": "C:\\Users\\sawaiz\\Desktop\\superMario64-TAS\\logs\\run_us_20260722_135536.csv",
      "rows": 342,
      "reached_star": true,
      "star_touch_sample": 224,
      "star_touch_vi": 538,
      "star_touch_action": 6404,
      "star_exit_sample": 228,
      "star_exit_vi": 546,
      "star_sample": 228,
      "star_vi": 546,
      "star_global_timer": 2360,
      "end_action": 4866,
      "end_x": -1979.313965,
      "end_y": -2518.0,
      "end_z": -2888.267822,
      "first_walking_sample": 101,
      "first_walking_vi": 292,
      "first_jump_sample": 135,
      "first_jump_vi": 360,
      "first_jump_kick_sample": 106,
      "first_jump_kick_vi": 302,
      "parity_hash": "a8cd7f07ef0fe5e4",
      "parity_checkpoints": 34,
      "result": "ties verified seed"
    },
    {
      "candidate": "window_start_155",
      "edit_count": 47,
      "csv": "C:\\Users\\sawaiz\\Desktop\\superMario64-TAS\\logs\\run_us_20260722_135541.csv",
      "rows": 342,
      "reached_star": true,
      "star_touch_sample": 224,
      "star_touch_vi": 538,
      "star_touch_action": 6404,
      "star_exit_sample": 228,
      "star_exit_vi": 546,
      "star_sample": 228,
      "star_vi": 546,
      "star_global_timer": 2360,
      "end_action": 4866,
      "end_x": -1972.896973,
      "end_y": -2518.0,
      "end_z": -2888.495117,
      "first_walking_sample": 101,
      "first_walking_vi": 292,
      "first_jump_sample": 135,
      "first_jump_vi": 360,
      "first_jump_kick_sample": 106,
      "first_jump_kick_vi": 302,
      "parity_hash": "bd69abbdafb26bf5",
      "parity_checkpoints": 34,
      "result": "ties verified seed"
    },
    {
      "candidate": "window_start_156",
      "edit_count": 46,
      "csv": "C:\\Users\\sawaiz\\Desktop\\superMario64-TAS\\logs\\run_us_20260722_135545.csv",
      "rows": 342,
      "reached_star": true,
      "star_touch_sample": 224,
      "star_touch_vi": 538,
      "star_touch_action": 6404,
      "star_exit_sample": 228,
      "star_exit_vi": 546,
      "star_sample": 228,
      "star_vi": 546,
      "star_global_timer": 2360,
      "end_action": 4866,
      "end_x": -1975.397827,
      "end_y": -2518.0,
      "end_z": -2888.433105,
      "first_walking_sample": 101,
      "first_walking_vi": 292,
      "first_jump_sample": 135,
      "first_jump_vi": 360,
      "first_jump_kick_sample": 106,
      "first_jump_kick_vi": 302,
      "parity_hash": "73b5c694af433323",
      "parity_checkpoints": 34,
      "result": "ties verified seed"
    },
    {
      "candidate": "window_start_157",
      "edit_count": 45,
      "csv": "C:\\Users\\sawaiz\\Desktop\\superMario64-TAS\\logs\\run_us_20260722_135550.csv",
      "rows": 342,
      "reached_star": true,
      "star_touch_sample": 226,
      "star_touch_vi": 542,
      "star_touch_action": 6404,
      "star_exit_sample": 229,
      "star_exit_vi": 548,
      "star_sample": 229,
      "star_vi": 548,
      "star_global_timer": 2362,
      "end_action": 4866,
      "end_x": -1971.154541,
      "end_y": -2518.0,
      "end_z": -2888.59082,
      "first_walking_sample": 101,
      "first_walking_vi": 292,
      "first_jump_sample": 135,
      "first_jump_vi": 360,
      "first_jump_kick_sample": 106,
      "first_jump_kick_vi": 302,
      "parity_hash": "401e1da3bee74492",
      "parity_checkpoints": 34,
      "result": "slower"
    },
    {
      "candidate": "window_start_158",
      "edit_count": 44,
      "csv": "C:\\Users\\sawaiz\\Desktop\\superMario64-TAS\\logs\\run_us_20260722_135555.csv",
      "rows": 342,
      "reached_star": true,
      "star_touch_sample": 226,
      "star_touch_vi": 542,
      "star_touch_action": 6404,
      "star_exit_sample": 229,
      "star_exit_vi": 548,
      "star_sample": 229,
      "star_vi": 548,
      "star_global_timer": 2362,
      "end_action": 4866,
      "end_x": -1970.373535,
      "end_y": -2518.0,
      "end_z": -2888.651855,
      "first_walking_sample": 101,
      "first_walking_vi": 292,
      "first_jump_sample": 135,
      "first_jump_vi": 360,
      "first_jump_kick_sample": 106,
      "first_jump_kick_vi": 302,
      "parity_hash": "abdfbcf55697bb1c",
      "parity_checkpoints": 34,
      "result": "slower"
    },
    {
      "candidate": "window_start_159",
      "edit_count": 43,
      "csv": "C:\\Users\\sawaiz\\Desktop\\superMario64-TAS\\logs\\run_us_20260722_135559.csv",
      "rows": 342,
      "reached_star": false,
      "star_touch_sample": null,
      "star_touch_vi": null,
      "star_touch_action": null,
      "star_exit_sample": null,
      "star_exit_vi": null,
      "star_sample": null,
      "star_vi": null,
      "star_global_timer": null,
      "end_action": 67109952,
      "end_x": -2508.070557,
      "end_y": -4358.400879,
      "end_z": -2506.06665,
      "first_walking_sample": 101,
      "first_walking_vi": 292,
      "first_jump_sample": 135,
      "first_jump_vi": 360,
      "first_jump_kick_sample": 106,
      "first_jump_kick_vi": 302,
      "parity_hash": "f74aaa9a3084fce7",
      "parity_checkpoints": 34,
      "result": "rejected: star not reached"
    },
    {
      "candidate": "window_start_160",
      "edit_count": 42,
      "csv": "C:\\Users\\sawaiz\\Desktop\\superMario64-TAS\\logs\\run_us_20260722_135604.csv",
      "rows": 342,
      "reached_star": false,
      "star_touch_sample": null,
      "star_touch_vi": null,
      "star_touch_action": null,
      "star_exit_sample": null,
      "star_exit_vi": null,
      "star_sample": null,
      "star_vi": null,
      "star_global_timer": null,
      "end_action": 67109952,
      "end_x": -2508.070557,
      "end_y": -4358.400879,
      "end_z": -2506.06665,
      "first_walking_sample": 101,
      "first_walking_vi": 292,
      "first_jump_sample": 135,
      "first_jump_vi": 360,
      "first_jump_kick_sample": 106,
      "first_jump_kick_vi": 302,
      "parity_hash": "f94e599219ceccd8",
      "parity_checkpoints": 34,
      "result": "rejected: star not reached"
    },
    {
      "candidate": "window_end_186",
      "edit_count": 38,
      "csv": "C:\\Users\\sawaiz\\Desktop\\superMario64-TAS\\logs\\run_us_20260722_135609.csv",
      "rows": 342,
      "reached_star": true,
      "star_touch_sample": 226,
      "star_touch_vi": 542,
      "star_touch_action": 6404,
      "star_exit_sample": 229,
      "star_exit_vi": 548,
      "star_sample": 229,
      "star_vi": 548,
      "star_global_timer": 2362,
      "end_action": 4866,
      "end_x": -1965.931885,
      "end_y": -2518.0,
      "end_z": -2888.786377,
      "first_walking_sample": 101,
      "first_walking_vi": 292,
      "first_jump_sample": 135,
      "first_jump_vi": 360,
      "first_jump_kick_sample": 106,
      "first_jump_kick_vi": 302,
      "parity_hash": "07276b55c63ce0e0",
      "parity_checkpoints": 34,
      "result": "slower"
    },
    {
      "candidate": "window_end_187",
      "edit_count": 39,
      "csv": "C:\\Users\\sawaiz\\Desktop\\superMario64-TAS\\logs\\run_us_20260722_135613.csv",
      "rows": 342,
      "reached_star": true,
      "star_touch_sample": 226,
      "star_touch_vi": 542,
      "star_touch_action": 6404,
      "star_exit_sample": 229,
      "star_exit_vi": 548,
      "star_sample": 229,
      "star_vi": 548,
      "star_global_timer": 2362,
      "end_action": 4866,
      "end_x": -1972.06543,
      "end_y": -2518.0,
      "end_z": -2888.979004,
      "first_walking_sample": 101,
      "first_walking_vi": 292,
      "first_jump_sample": 135,
      "first_jump_vi": 360,
      "first_jump_kick_sample": 106,
      "first_jump_kick_vi": 302,
      "parity_hash": "5fbb61cc25141ace",
      "parity_checkpoints": 34,
      "result": "slower"
    },
    {
      "candidate": "window_end_188",
      "edit_count": 40,
      "csv": "C:\\Users\\sawaiz\\Desktop\\superMario64-TAS\\logs\\run_us_20260722_135618.csv",
      "rows": 342,
      "reached_star": true,
      "star_touch_sample": 226,
      "star_touch_vi": 542,
      "star_touch_action": 6404,
      "star_exit_sample": 229,
      "star_exit_vi": 548,
      "star_sample": 229,
      "star_vi": 548,
      "star_global_timer": 2362,
      "end_action": 4866,
      "end_x": -1970.32373,
      "end_y": -2518.0,
      "end_z": -2888.652344,
      "first_walking_sample": 101,
      "first_walking_vi": 292,
      "first_jump_sample": 135,
      "first_jump_vi": 360,
      "first_jump_kick_sample": 106,
      "first_jump_kick_vi": 302,
      "parity_hash": "0de6a5d473c1cdd2",
      "parity_checkpoints": 34,
      "result": "slower"
    },
    {
      "candidate": "window_end_189",
      "edit_count": 41,
      "csv": "C:\\Users\\sawaiz\\Desktop\\superMario64-TAS\\logs\\run_us_20260722_135622.csv",
      "rows": 342,
      "reached_star": true,
      "star_touch_sample": 226,
      "star_touch_vi": 542,
      "star_touch_action": 6404,
      "star_exit_sample": 229,
      "star_exit_vi": 548,
      "star_sample": 229,
      "star_vi": 548,
      "star_global_timer": 2362,
      "end_action": 4866,
      "end_x": -1965.204346,
      "end_y": -2518.0,
      "end_z": -2888.817627,
      "first_walking_sample": 101,
      "first_walking_vi": 292,
      "first_jump_sample": 135,
      "first_jump_vi": 360,
      "first_jump_kick_sample": 106,
      "first_jump_kick_vi": 302,
      "parity_hash": "a4f88b9b17897fc1",
      "parity_checkpoints": 34,
      "result": "slower"
    },
    {
      "candidate": "window_end_190",
      "edit_count": 42,
      "csv": "C:\\Users\\sawaiz\\Desktop\\superMario64-TAS\\logs\\run_us_20260722_135627.csv",
      "rows": 342,
      "reached_star": false,
      "star_touch_sample": null,
      "star_touch_vi": null,
      "star_touch_action": null,
      "star_exit_sample": null,
      "star_exit_vi": null,
      "star_sample": null,
      "star_vi": null,
      "star_global_timer": null,
      "end_action": 67109952,
      "end_x": -2508.06665,
      "end_y": -4358.400879,
      "end_z": -2506.075439,
      "first_walking_sample": 101,
      "first_walking_vi": 292,
      "first_jump_sample": 135,
      "first_jump_vi": 360,
      "first_jump_kick_sample": 106,
      "first_jump_kick_vi": 302,
      "parity_hash": "8342db0c618b4589",
      "parity_checkpoints": 34,
      "result": "rejected: star not reached"
    },
    {
      "candidate": "window_end_191",
      "edit_count": 43,
      "csv": "C:\\Users\\sawaiz\\Desktop\\superMario64-TAS\\logs\\run_us_20260722_135631.csv",
      "rows": 342,
      "reached_star": false,
      "star_touch_sample": null,
      "star_touch_vi": null,
      "star_touch_action": null,
      "star_exit_sample": null,
      "star_exit_vi": null,
      "star_sample": null,
      "star_vi": null,
      "star_global_timer": null,
      "end_action": 67109952,
      "end_x": -2508.06665,
      "end_y": -4358.400879,
      "end_z": -2506.075439,
      "first_walking_sample": 101,
      "first_walking_vi": 292,
      "first_jump_sample": 135,
      "first_jump_vi": 360,
      "first_jump_kick_sample": 106,
      "first_jump_kick_vi": 302,
      "parity_hash": "f5b1e39849ed482b",
      "parity_checkpoints": 34,
      "result": "rejected: star not reached"
    },
    {
      "candidate": "window_end_192",
      "edit_count": 44,
      "csv": "C:\\Users\\sawaiz\\Desktop\\superMario64-TAS\\logs\\run_us_20260722_135636.csv",
      "rows": 342,
      "reached_star": false,
      "star_touch_sample": null,
      "star_touch_vi": null,
      "star_touch_action": null,
      "star_exit_sample": null,
      "star_exit_vi": null,
      "star_sample": null,
      "star_vi": null,
      "star_global_timer": null,
      "end_action": 67109952,
      "end_x": -2508.06665,
      "end_y": -4358.400879,
      "end_z": -2506.075439,
      "first_walking_sample": 101,
      "first_walking_vi": 292,
      "first_jump_sample": 135,
      "first_jump_vi": 360,
      "first_jump_kick_sample": 106,
      "first_jump_kick_vi": 302,
      "parity_hash": "0aff931d73f2084a",
      "parity_checkpoints": 34,
      "result": "rejected: star not reached"
    },
    {
      "candidate": "window_end_193",
      "edit_count": 45,
      "csv": "C:\\Users\\sawaiz\\Desktop\\superMario64-TAS\\logs\\run_us_20260722_135641.csv",
      "rows": 342,
      "reached_star": true,
      "star_touch_sample": 226,
      "star_touch_vi": 542,
      "star_touch_action": 6404,
      "star_exit_sample": 228,
      "star_exit_vi": 546,
      "star_sample": 228,
      "star_vi": 546,
      "star_global_timer": 2362,
      "end_action": 4866,
      "end_x": -1974.669067,
      "end_y": -2518.0,
      "end_z": -2888.51416,
      "first_walking_sample": 101,
      "first_walking_vi": 292,
      "first_jump_sample": 135,
      "first_jump_vi": 360,
      "first_jump_kick_sample": 106,
      "first_jump_kick_vi": 302,
      "parity_hash": "cc49be26f3baf946",
      "parity_checkpoints": 34,
      "result": "slower"
    },
    {
      "candidate": "window_end_194",
      "edit_count": 46,
      "csv": "C:\\Users\\sawaiz\\Desktop\\superMario64-TAS\\logs\\run_us_20260722_135645.csv",
      "rows": 342,
      "reached_star": true,
      "star_touch_sample": 226,
      "star_touch_vi": 542,
      "star_touch_action": 6404,
      "star_exit_sample": 229,
      "star_exit_vi": 548,
      "star_sample": 229,
      "star_vi": 548,
      "star_global_timer": 2362,
      "end_action": 4866,
      "end_x": -1969.025635,
      "end_y": -2518.0,
      "end_z": -2889.104492,
      "first_walking_sample": 101,
      "first_walking_vi": 292,
      "first_jump_sample": 135,
      "first_jump_vi": 360,
      "first_jump_kick_sample": 106,
      "first_jump_kick_vi": 302,
      "parity_hash": "685afa392e4af6b5",
      "parity_checkpoints": 34,
      "result": "slower"
    },
    {
      "candidate": "window_end_195",
      "edit_count": 47,
      "csv": "C:\\Users\\sawaiz\\Desktop\\superMario64-TAS\\logs\\run_us_20260722_135650.csv",
      "rows": 342,
      "reached_star": true,
      "star_touch_sample": 226,
      "star_touch_vi": 542,
      "star_touch_action": 6404,
      "star_exit_sample": 228,
      "star_exit_vi": 546,
      "star_sample": 228,
      "star_vi": 546,
      "star_global_timer": 2362,
      "end_action": 4866,
      "end_x": -1976.137085,
      "end_y": -2518.0,
      "end_z": -2888.451416,
      "first_walking_sample": 101,
      "first_walking_vi": 292,
      "first_jump_sample": 135,
      "first_jump_vi": 360,
      "first_jump_kick_sample": 106,
      "first_jump_kick_vi": 302,
      "parity_hash": "95445e6e99668a13",
      "parity_checkpoints": 34,
      "result": "slower"
    },
    {
      "candidate": "window_end_196",
      "edit_count": 48,
      "csv": "C:\\Users\\sawaiz\\Desktop\\superMario64-TAS\\logs\\run_us_20260722_135654.csv",
      "rows": 342,
      "reached_star": true,
      "star_touch_sample": 226,
      "star_touch_vi": 542,
      "star_touch_action": 6404,
      "star_exit_sample": 228,
      "star_exit_vi": 546,
      "star_sample": 228,
      "star_vi": 546,
      "star_global_timer": 2362,
      "end_action": 4866,
      "end_x": -1973.977539,
      "end_y": -2518.0,
      "end_z": -2888.494629,
      "first_walking_sample": 101,
      "first_walking_vi": 292,
      "first_jump_sample": 135,
      "first_jump_vi": 360,
      "first_jump_kick_sample": 106,
      "first_jump_kick_vi": 302,
      "parity_hash": "e296747052f12b1a",
      "parity_checkpoints": 34,
      "result": "slower"
    },
    {
      "candidate": "window_end_197",
      "edit_count": 49,
      "csv": "C:\\Users\\sawaiz\\Desktop\\superMario64-TAS\\logs\\run_us_20260722_135659.csv",
      "rows": 342,
      "reached_star": true,
      "star_touch_sample": 226,
      "star_touch_vi": 542,
      "star_touch_action": 6404,
      "star_exit_sample": 228,
      "star_exit_vi": 546,
      "star_sample": 228,
      "star_vi": 546,
      "star_global_timer": 2362,
      "end_action": 4866,
      "end_x": -1971.880371,
      "end_y": -2518.0,
      "end_z": -2888.958252,
      "first_walking_sample": 101,
      "first_walking_vi": 292,
      "first_jump_sample": 135,
      "first_jump_vi": 360,
      "first_jump_kick_sample": 106,
      "first_jump_kick_vi": 302,
      "parity_hash": "2d452b2e9c7970fa",
      "parity_checkpoints": 34,
      "result": "slower"
    },
    {
      "candidate": "window_end_198",
      "edit_count": 50,
      "csv": "C:\\Users\\sawaiz\\Desktop\\superMario64-TAS\\logs\\run_us_20260722_135704.csv",
      "rows": 342,
      "reached_star": false,
      "star_touch_sample": null,
      "star_touch_vi": null,
      "star_touch_action": null,
      "star_exit_sample": null,
      "star_exit_vi": null,
      "star_sample": null,
      "star_vi": null,
      "star_global_timer": null,
      "end_action": 67109952,
      "end_x": -2508.06665,
      "end_y": -4358.400879,
      "end_z": -2506.075439,
      "first_walking_sample": 101,
      "first_walking_vi": 292,
      "first_jump_sample": 135,
      "first_jump_vi": 360,
      "first_jump_kick_sample": 106,
      "first_jump_kick_vi": 302,
      "parity_hash": "a4a2a9fff7c6675b",
      "parity_checkpoints": 34,
      "result": "rejected: star not reached"
    },
    {
      "candidate": "window_end_199",
      "edit_count": 51,
      "csv": "C:\\Users\\sawaiz\\Desktop\\superMario64-TAS\\logs\\run_us_20260722_135709.csv",
      "rows": 342,
      "reached_star": true,
      "star_touch_sample": 226,
      "star_touch_vi": 542,
      "star_touch_action": 6404,
      "star_exit_sample": 228,
      "star_exit_vi": 546,
      "star_sample": 228,
      "star_vi": 546,
      "star_global_timer": 2362,
      "end_action": 4866,
      "end_x": -1976.365356,
      "end_y": -2518.0,
      "end_z": -2888.44165,
      "first_walking_sample": 101,
      "first_walking_vi": 292,
      "first_jump_sample": 135,
      "first_jump_vi": 360,
      "first_jump_kick_sample": 106,
      "first_jump_kick_vi": 302,
      "parity_hash": "9b165129a386f5d8",
      "parity_checkpoints": 34,
      "result": "slower"
    },
    {
      "candidate": "window_end_200",
      "edit_count": 52,
      "csv": "C:\\Users\\sawaiz\\Desktop\\superMario64-TAS\\logs\\run_us_20260722_135713.csv",
      "rows": 342,
      "reached_star": true,
      "star_touch_sample": 226,
      "star_touch_vi": 542,
      "star_touch_action": 6404,
      "star_exit_sample": 228,
      "star_exit_vi": 546,
      "star_sample": 228,
      "star_vi": 546,
      "star_global_timer": 2362,
      "end_action": 4866,
      "end_x": -1974.053467,
      "end_y": -2518.0,
      "end_z": -2888.894287,
      "first_walking_sample": 101,
      "first_walking_vi": 292,
      "first_jump_sample": 135,
      "first_jump_vi": 360,
      "first_jump_kick_sample": 106,
      "first_jump_kick_vi": 302,
      "parity_hash": "9564da2f944521a4",
      "parity_checkpoints": 34,
      "result": "slower"
    },
    {
      "candidate": "window_end_202",
      "edit_count": 54,
      "csv": "C:\\Users\\sawaiz\\Desktop\\superMario64-TAS\\logs\\run_us_20260722_135718.csv",
      "rows": 342,
      "reached_star": true,
      "star_touch_sample": 226,
      "star_touch_vi": 542,
      "star_touch_action": 6404,
      "star_exit_sample": 228,
      "star_exit_vi": 546,
      "star_sample": 228,
      "star_vi": 546,
      "star_global_timer": 2362,
      "end_action": 4866,
      "end_x": -1976.757202,
      "end_y": -2518.0,
      "end_z": -2888.431396,
      "first_walking_sample": 101,
      "first_walking_vi": 292,
      "first_jump_sample": 135,
      "first_jump_vi": 360,
      "first_jump_kick_sample": 106,
      "first_jump_kick_vi": 302,
      "parity_hash": "5832fdcd730ee71a",
      "parity_checkpoints": 34,
      "result": "slower"
    },
    {
      "candidate": "window_end_203",
      "edit_count": 55,
      "csv": "C:\\Users\\sawaiz\\Desktop\\superMario64-TAS\\logs\\run_us_20260722_135723.csv",
      "rows": 342,
      "reached_star": false,
      "star_touch_sample": null,
      "star_touch_vi": null,
      "star_touch_action": null,
      "star_exit_sample": null,
      "star_exit_vi": null,
      "star_sample": null,
      "star_vi": null,
      "star_global_timer": null,
      "end_action": 67109952,
      "end_x": -2508.06665,
      "end_y": -4358.400879,
      "end_z": -2506.075439,
      "first_walking_sample": 101,
      "first_walking_vi": 292,
      "first_jump_sample": 135,
      "first_jump_vi": 360,
      "first_jump_kick_sample": 106,
      "first_jump_kick_vi": 302,
      "parity_hash": "9894eb9e36cdb7c9",
      "parity_checkpoints": 34,
      "result": "rejected: star not reached"
    },
    {
      "candidate": "window_end_204",
      "edit_count": 56,
      "csv": "C:\\Users\\sawaiz\\Desktop\\superMario64-TAS\\logs\\run_us_20260722_135728.csv",
      "rows": 342,
      "reached_star": true,
      "star_touch_sample": 226,
      "star_touch_vi": 542,
      "star_touch_action": 6404,
      "star_exit_sample": 228,
      "star_exit_vi": 546,
      "star_sample": 228,
      "star_vi": 546,
      "star_global_timer": 2362,
      "end_action": 4866,
      "end_x": -1977.239136,
      "end_y": -2518.0,
      "end_z": -2888.813477,
      "first_walking_sample": 101,
      "first_walking_vi": 292,
      "first_jump_sample": 135,
      "first_jump_vi": 360,
      "first_jump_kick_sample": 106,
      "first_jump_kick_vi": 302,
      "parity_hash": "de38bf94512382b0",
      "parity_checkpoints": 34,
      "result": "slower"
    },
    {
      "candidate": "window_end_205",
      "edit_count": 57,
      "csv": "C:\\Users\\sawaiz\\Desktop\\superMario64-TAS\\logs\\run_us_20260722_135733.csv",
      "rows": 342,
      "reached_star": true,
      "star_touch_sample": 226,
      "star_touch_vi": 542,
      "star_touch_action": 6404,
      "star_exit_sample": 229,
      "star_exit_vi": 548,
      "star_sample": 229,
      "star_vi": 548,
      "star_global_timer": 2362,
      "end_action": 4866,
      "end_x": -1969.994141,
      "end_y": -2518.0,
      "end_z": -2888.666504,
      "first_walking_sample": 101,
      "first_walking_vi": 292,
      "first_jump_sample": 135,
      "first_jump_vi": 360,
      "first_jump_kick_sample": 106,
      "first_jump_kick_vi": 302,
      "parity_hash": "679bf6bf1107b22f",
      "parity_checkpoints": 34,
      "result": "slower"
    },
    {
      "candidate": "window_end_206",
      "edit_count": 58,
      "csv": "C:\\Users\\sawaiz\\Desktop\\superMario64-TAS\\logs\\run_us_20260722_135737.csv",
      "rows": 342,
      "reached_star": true,
      "star_touch_sample": 226,
      "star_touch_vi": 542,
      "star_touch_action": 6404,
      "star_exit_sample": 229,
      "star_exit_vi": 548,
      "star_sample": 229,
      "star_vi": 548,
      "star_global_timer": 2362,
      "end_action": 4866,
      "end_x": -1968.840332,
      "end_y": -2518.0,
      "end_z": -2889.112305,
      "first_walking_sample": 101,
      "first_walking_vi": 292,
      "first_jump_sample": 135,
      "first_jump_vi": 360,
      "first_jump_kick_sample": 106,
      "first_jump_kick_vi": 302,
      "parity_hash": "2151d435b019a47c",
      "parity_checkpoints": 34,
      "result": "slower"
    },
    {
      "candidate": "window_end_207",
      "edit_count": 59,
      "csv": "C:\\Users\\sawaiz\\Desktop\\superMario64-TAS\\logs\\run_us_20260722_135741.csv",
      "rows": 342,
      "reached_star": true,
      "star_touch_sample": 226,
      "star_touch_vi": 542,
      "star_touch_action": 6404,
      "star_exit_sample": 229,
      "star_exit_vi": 548,
      "star_sample": 229,
      "star_vi": 548,
      "star_global_timer": 2362,
      "end_action": 4866,
      "end_x": -1970.854248,
      "end_y": -2518.0,
      "end_z": -2888.629639,
      "first_walking_sample": 101,
      "first_walking_vi": 292,
      "first_jump_sample": 135,
      "first_jump_vi": 360,
      "first_jump_kick_sample": 106,
      "first_jump_kick_vi": 302,
      "parity_hash": "67720b39c9c50184",
      "parity_checkpoints": 34,
      "result": "slower"
    },
    {
      "candidate": "window_end_208",
      "edit_count": 60,
      "csv": "C:\\Users\\sawaiz\\Desktop\\superMario64-TAS\\logs\\run_us_20260722_135746.csv",
      "rows": 342,
      "reached_star": true,
      "star_touch_sample": 226,
      "star_touch_vi": 542,
      "star_touch_action": 6404,
      "star_exit_sample": 229,
      "star_exit_vi": 548,
      "star_sample": 229,
      "star_vi": 548,
      "star_global_timer": 2362,
      "end_action": 4866,
      "end_x": -1969.786377,
      "end_y": -2518.0,
      "end_z": -2888.647705,
      "first_walking_sample": 101,
      "first_walking_vi": 292,
      "first_jump_sample": 135,
      "first_jump_vi": 360,
      "first_jump_kick_sample": 106,
      "first_jump_kick_vi": 302,
      "parity_hash": "2f7e71dadf978dc3",
      "parity_checkpoints": 34,
      "result": "slower"
    },
    {
      "candidate": "window_end_209",
      "edit_count": 61,
      "csv": "C:\\Users\\sawaiz\\Desktop\\superMario64-TAS\\logs\\run_us_20260722_135751.csv",
      "rows": 342,
      "reached_star": false,
      "star_touch_sample": null,
      "star_touch_vi": null,
      "star_touch_action": null,
      "star_exit_sample": null,
      "star_exit_vi": null,
      "star_sample": null,
      "star_vi": null,
      "star_global_timer": null,
      "end_action": 67109952,
      "end_x": -2508.06665,
      "end_y": -4358.400879,
      "end_z": -2506.075439,
      "first_walking_sample": 101,
      "first_walking_vi": 292,
      "first_jump_sample": 135,
      "first_jump_vi": 360,
      "first_jump_kick_sample": 106,
      "first_jump_kick_vi": 302,
      "parity_hash": "19299a97cf7e7665",
      "parity_checkpoints": 34,
      "result": "rejected: star not reached"
    },
    {
      "candidate": "window_end_210",
      "edit_count": 62,
      "csv": "C:\\Users\\sawaiz\\Desktop\\superMario64-TAS\\logs\\run_us_20260722_135755.csv",
      "rows": 342,
      "reached_star": true,
      "star_touch_sample": 226,
      "star_touch_vi": 542,
      "star_touch_action": 6404,
      "star_exit_sample": 229,
      "star_exit_vi": 548,
      "star_sample": 229,
      "star_vi": 548,
      "star_global_timer": 2362,
      "end_action": 4866,
      "end_x": -1970.675049,
      "end_y": -2518.0,
      "end_z": -2889.038574,
      "first_walking_sample": 101,
      "first_walking_vi": 292,
      "first_jump_sample": 135,
      "first_jump_vi": 360,
      "first_jump_kick_sample": 106,
      "first_jump_kick_vi": 302,
      "parity_hash": "e09a6d1a7920c78d",
      "parity_checkpoints": 34,
      "result": "slower"
    },
    {
      "candidate": "window_end_211",
      "edit_count": 63,
      "csv": "C:\\Users\\sawaiz\\Desktop\\superMario64-TAS\\logs\\run_us_20260722_135800.csv",
      "rows": 342,
      "reached_star": true,
      "star_touch_sample": 226,
      "star_touch_vi": 542,
      "star_touch_action": 6404,
      "star_exit_sample": 229,
      "star_exit_vi": 548,
      "star_sample": 229,
      "star_vi": 548,
      "star_global_timer": 2362,
      "end_action": 4866,
      "end_x": -1970.675049,
      "end_y": -2518.0,
      "end_z": -2889.038574,
      "first_walking_sample": 101,
      "first_walking_vi": 292,
      "first_jump_sample": 135,
      "first_jump_vi": 360,
      "first_jump_kick_sample": 106,
      "first_jump_kick_vi": 302,
      "parity_hash": "9d6287eb8eac6729",
      "parity_checkpoints": 34,
      "result": "slower"
    },
    {
      "candidate": "window_end_212",
      "edit_count": 64,
      "csv": "C:\\Users\\sawaiz\\Desktop\\superMario64-TAS\\logs\\run_us_20260722_135804.csv",
      "rows": 342,
      "reached_star": true,
      "star_touch_sample": 226,
      "star_touch_vi": 542,
      "star_touch_action": 6404,
      "star_exit_sample": 229,
      "star_exit_vi": 548,
      "star_sample": 229,
      "star_vi": 548,
      "star_global_timer": 2362,
      "end_action": 4866,
      "end_x": -1968.948975,
      "end_y": -2518.0,
      "end_z": -2889.10791,
      "first_walking_sample": 101,
      "first_walking_vi": 292,
      "first_jump_sample": 135,
      "first_jump_vi": 360,
      "first_jump_kick_sample": 106,
      "first_jump_kick_vi": 302,
      "parity_hash": "d37868642c85ccb8",
      "parity_checkpoints": 34,
      "result": "slower"
    },
    {
      "candidate": "window_end_213",
      "edit_count": 65,
      "csv": "C:\\Users\\sawaiz\\Desktop\\superMario64-TAS\\logs\\run_us_20260722_135809.csv",
      "rows": 342,
      "reached_star": false,
      "star_touch_sample": null,
      "star_touch_vi": null,
      "star_touch_action": null,
      "star_exit_sample": null,
      "star_exit_vi": null,
      "star_sample": null,
      "star_vi": null,
      "star_global_timer": null,
      "end_action": 67109952,
      "end_x": -2508.070557,
      "end_y": -4358.400879,
      "end_z": -2506.06665,
      "first_walking_sample": 101,
      "first_walking_vi": 292,
      "first_jump_sample": 135,
      "first_jump_vi": 360,
      "first_jump_kick_sample": 106,
      "first_jump_kick_vi": 302,
      "parity_hash": "b8e09a4c2b5d71a7",
      "parity_checkpoints": 34,
      "result": "rejected: star not reached"
    },
    {
      "candidate": "launch_full_dx-4_dy+0",
      "edit_count": 67,
      "csv": "C:\\Users\\sawaiz\\Desktop\\superMario64-TAS\\logs\\run_us_20260722_135813.csv",
      "rows": 342,
      "reached_star": false,
      "star_touch_sample": null,
      "star_touch_vi": null,
      "star_touch_action": null,
      "star_exit_sample": null,
      "star_exit_vi": null,
      "star_sample": null,
      "star_vi": null,
      "star_global_timer": null,
      "end_action": 67109952,
      "end_x": -2115.866455,
      "end_y": 2560.0,
      "end_z": -1616.106323,
      "first_walking_sample": 101,
      "first_walking_vi": 292,
      "first_jump_sample": 135,
      "first_jump_vi": 360,
      "first_jump_kick_sample": 106,
      "first_jump_kick_vi": 302,
      "parity_hash": "e934f2a34a953210",
      "parity_checkpoints": 34,
      "result": "rejected: star not reached"
    },
    {
      "candidate": "launch_full_dx-2_dy+0",
      "edit_count": 67,
      "csv": "C:\\Users\\sawaiz\\Desktop\\superMario64-TAS\\logs\\run_us_20260722_135818.csv",
      "rows": 342,
      "reached_star": false,
      "star_touch_sample": null,
      "star_touch_vi": null,
      "star_touch_action": null,
      "star_exit_sample": null,
      "star_exit_vi": null,
      "star_sample": null,
      "star_vi": null,
      "star_global_timer": null,
      "end_action": 67109952,
      "end_x": -2115.410156,
      "end_y": 2560.0,
      "end_z": -1616.290283,
      "first_walking_sample": 101,
      "first_walking_vi": 292,
      "first_jump_sample": 135,
      "first_jump_vi": 360,
      "first_jump_kick_sample": 106,
      "first_jump_kick_vi": 302,
      "parity_hash": "aa70ab90496ee599",
      "parity_checkpoints": 34,
      "result": "rejected: star not reached"
    },
    {
      "candidate": "launch_full_dx+2_dy+0",
      "edit_count": 67,
      "csv": "C:\\Users\\sawaiz\\Desktop\\superMario64-TAS\\logs\\run_us_20260722_135822.csv",
      "rows": 342,
      "reached_star": false,
      "star_touch_sample": null,
      "star_touch_vi": null,
      "star_touch_action": null,
      "star_exit_sample": null,
      "star_exit_vi": null,
      "star_sample": null,
      "star_vi": null,
      "star_global_timer": null,
      "end_action": 67109952,
      "end_x": -2095.447998,
      "end_y": 2560.0,
      "end_z": -1623.480469,
      "first_walking_sample": 101,
      "first_walking_vi": 292,
      "first_jump_sample": 135,
      "first_jump_vi": 360,
      "first_jump_kick_sample": 106,
      "first_jump_kick_vi": 302,
      "parity_hash": "5060cc1fff8d01dc",
      "parity_checkpoints": 34,
      "result": "rejected: star not reached"
    },
    {
      "candidate": "launch_full_dx+4_dy+0",
      "edit_count": 67,
      "csv": "C:\\Users\\sawaiz\\Desktop\\superMario64-TAS\\logs\\run_us_20260722_135827.csv",
      "rows": 342,
      "reached_star": false,
      "star_touch_sample": null,
      "star_touch_vi": null,
      "star_touch_action": null,
      "star_exit_sample": null,
      "star_exit_vi": null,
      "star_sample": null,
      "star_vi": null,
      "star_global_timer": null,
      "end_action": 67109952,
      "end_x": -2095.130615,
      "end_y": 2560.0,
      "end_z": -1623.693115,
      "first_walking_sample": 101,
      "first_walking_vi": 292,
      "first_jump_sample": 135,
      "first_jump_vi": 360,
      "first_jump_kick_sample": 106,
      "first_jump_kick_vi": 302,
      "parity_hash": "fa225cc2f99d43d0",
      "parity_checkpoints": 34,
      "result": "rejected: star not reached"
    },
    {
      "candidate": "launch_full_dx+0_dy-8",
      "edit_count": 67,
      "csv": "C:\\Users\\sawaiz\\Desktop\\superMario64-TAS\\logs\\run_us_20260722_135831.csv",
      "rows": 342,
      "reached_star": false,
      "star_touch_sample": null,
      "star_touch_vi": null,
      "star_touch_action": null,
      "star_exit_sample": null,
      "star_exit_vi": null,
      "star_sample": null,
      "star_vi": null,
      "star_global_timer": null,
      "end_action": 67109952,
      "end_x": -2087.489746,
      "end_y": 2560.0,
      "end_z": -1629.012329,
      "first_walking_sample": 101,
      "first_walking_vi": 292,
      "first_jump_sample": 135,
      "first_jump_vi": 360,
      "first_jump_kick_sample": 106,
      "first_jump_kick_vi": 302,
      "parity_hash": "bbd3837282094df3",
      "parity_checkpoints": 34,
      "result": "rejected: star not reached"
    },
    {
      "candidate": "launch_full_dx+0_dy-4",
      "edit_count": 67,
      "csv": "C:\\Users\\sawaiz\\Desktop\\superMario64-TAS\\logs\\run_us_20260722_135837.csv",
      "rows": 342,
      "reached_star": false,
      "star_touch_sample": null,
      "star_touch_vi": null,
      "star_touch_action": null,
      "star_exit_sample": null,
      "star_exit_vi": null,
      "star_sample": null,
      "star_vi": null,
      "star_global_timer": null,
      "end_action": 67109952,
      "end_x": -2089.988525,
      "end_y": 2560.0,
      "end_z": -1628.874268,
      "first_walking_sample": 101,
      "first_walking_vi": 292,
      "first_jump_sample": 135,
      "first_jump_vi": 360,
      "first_jump_kick_sample": 106,
      "first_jump_kick_vi": 302,
      "parity_hash": "e1ce30172f3643ca",
      "parity_checkpoints": 34,
      "result": "rejected: star not reached"
    },
    {
      "candidate": "launch_full_dx+0_dy+4",
      "edit_count": 67,
      "csv": "C:\\Users\\sawaiz\\Desktop\\superMario64-TAS\\logs\\run_us_20260722_135841.csv",
      "rows": 342,
      "reached_star": false,
      "star_touch_sample": null,
      "star_touch_vi": null,
      "star_touch_action": null,
      "star_exit_sample": null,
      "star_exit_vi": null,
      "star_sample": null,
      "star_vi": null,
      "star_global_timer": null,
      "end_action": 50333838,
      "end_x": -5127.527344,
      "end_y": 279.846313,
      "end_z": 685.719727,
      "first_walking_sample": 101,
      "first_walking_vi": 292,
      "first_jump_sample": 135,
      "first_jump_vi": 360,
      "first_jump_kick_sample": 106,
      "first_jump_kick_vi": 302,
      "parity_hash": "f15e6357aa272860",
      "parity_checkpoints": 34,
      "result": "rejected: star not reached"
    },
    {
      "candidate": "launch_full_dx+0_dy+8",
      "edit_count": 67,
      "csv": "C:\\Users\\sawaiz\\Desktop\\superMario64-TAS\\logs\\run_us_20260722_135846.csv",
      "rows": 342,
      "reached_star": false,
      "star_touch_sample": null,
      "star_touch_vi": null,
      "star_touch_action": null,
      "star_exit_sample": null,
      "star_exit_vi": null,
      "star_sample": null,
      "star_vi": null,
      "star_global_timer": null,
      "end_action": 67109952,
      "end_x": -2086.633789,
      "end_y": 2560.0,
      "end_z": -1628.813477,
      "first_walking_sample": 101,
      "first_walking_vi": 292,
      "first_jump_sample": 135,
      "first_jump_vi": 360,
      "first_jump_kick_sample": 106,
      "first_jump_kick_vi": 302,
      "parity_hash": "fe96b8ca13ff02e7",
      "parity_checkpoints": 34,
      "result": "rejected: star not reached"
    },
    {
      "candidate": "launch_suffix_137_dx-2_dy+0",
      "edit_count": 65,
      "csv": "C:\\Users\\sawaiz\\Desktop\\superMario64-TAS\\logs\\run_us_20260722_135850.csv",
      "rows": 342,
      "reached_star": false,
      "star_touch_sample": null,
      "star_touch_vi": null,
      "star_touch_action": null,
      "star_exit_sample": null,
      "star_exit_vi": null,
      "star_sample": null,
      "star_vi": null,
      "star_global_timer": null,
      "end_action": 67109952,
      "end_x": -2095.35791,
      "end_y": 2560.0,
      "end_z": -1623.457886,
      "first_walking_sample": 101,
      "first_walking_vi": 292,
      "first_jump_sample": 135,
      "first_jump_vi": 360,
      "first_jump_kick_sample": 106,
      "first_jump_kick_vi": 302,
      "parity_hash": "f618053a4e170e98",
      "parity_checkpoints": 34,
      "result": "rejected: star not reached"
    },
    {
      "candidate": "launch_suffix_137_dx+2_dy+0",
      "edit_count": 65,
      "csv": "C:\\Users\\sawaiz\\Desktop\\superMario64-TAS\\logs\\run_us_20260722_135855.csv",
      "rows": 342,
      "reached_star": false,
      "star_touch_sample": null,
      "star_touch_vi": null,
      "star_touch_action": null,
      "star_exit_sample": null,
      "star_exit_vi": null,
      "star_sample": null,
      "star_vi": null,
      "star_global_timer": null,
      "end_action": 67109952,
      "end_x": -2095.003418,
      "end_y": 2560.0,
      "end_z": -1623.375244,
      "first_walking_sample": 101,
      "first_walking_vi": 292,
      "first_jump_sample": 135,
      "first_jump_vi": 360,
      "first_jump_kick_sample": 106,
      "first_jump_kick_vi": 302,
      "parity_hash": "82c4bc29061c8e15",
      "parity_checkpoints": 34,
      "result": "rejected: star not reached"
    },
    {
      "candidate": "launch_suffix_137_dx+0_dy-4",
      "edit_count": 65,
      "csv": "C:\\Users\\sawaiz\\Desktop\\superMario64-TAS\\logs\\run_us_20260722_135900.csv",
      "rows": 342,
      "reached_star": false,
      "star_touch_sample": null,
      "star_touch_vi": null,
      "star_touch_action": null,
      "star_exit_sample": null,
      "star_exit_vi": null,
      "star_sample": null,
      "star_vi": null,
      "star_global_timer": null,
      "end_action": 67109952,
      "end_x": -2087.321533,
      "end_y": 2560.0,
      "end_z": -1628.970459,
      "first_walking_sample": 101,
      "first_walking_vi": 292,
      "first_jump_sample": 135,
      "first_jump_vi": 360,
      "first_jump_kick_sample": 106,
      "first_jump_kick_vi": 302,
      "parity_hash": "d7147e87e1457e31",
      "parity_checkpoints": 34,
      "result": "rejected: star not reached"
    },
    {
      "candidate": "launch_suffix_137_dx+0_dy+4",
      "edit_count": 65,
      "csv": "C:\\Users\\sawaiz\\Desktop\\superMario64-TAS\\logs\\run_us_20260722_135904.csv",
      "rows": 342,
      "reached_star": false,
      "star_touch_sample": null,
      "star_touch_vi": null,
      "star_touch_action": null,
      "star_exit_sample": null,
      "star_exit_vi": null,
      "star_sample": null,
      "star_vi": null,
      "star_global_timer": null,
      "end_action": 50333838,
      "end_x": -5128.963379,
      "end_y": 279.264038,
      "end_z": 680.568542,
      "first_walking_sample": 101,
      "first_walking_vi": 292,
      "first_jump_sample": 135,
      "first_jump_vi": 360,
      "first_jump_kick_sample": 106,
      "first_jump_kick_vi": 302,
      "parity_hash": "8d24c3f8e06591fa",
      "parity_checkpoints": 34,
      "result": "rejected: star not reached"
    },
    {
      "candidate": "launch_suffix_140_dx-2_dy+0",
      "edit_count": 62,
      "csv": "C:\\Users\\sawaiz\\Desktop\\superMario64-TAS\\logs\\run_us_20260722_135909.csv",
      "rows": 342,
      "reached_star": false,
      "star_touch_sample": null,
      "star_touch_vi": null,
      "star_touch_action": null,
      "star_exit_sample": null,
      "star_exit_vi": null,
      "star_sample": null,
      "star_vi": null,
      "star_global_timer": null,
      "end_action": 8651858,
      "end_x": -2072.54541,
      "end_y": 2560.0,
      "end_z": -1576.468628,
      "first_walking_sample": 101,
      "first_walking_vi": 292,
      "first_jump_sample": 135,
      "first_jump_vi": 360,
      "first_jump_kick_sample": 106,
      "first_jump_kick_vi": 302,
      "parity_hash": "3c6e9132dbb6278c",
      "parity_checkpoints": 34,
      "result": "rejected: star not reached"
    },
    {
      "candidate": "launch_suffix_140_dx+2_dy+0",
      "edit_count": 62,
      "csv": "C:\\Users\\sawaiz\\Desktop\\superMario64-TAS\\logs\\run_us_20260722_135913.csv",
      "rows": 342,
      "reached_star": false,
      "star_touch_sample": null,
      "star_touch_vi": null,
      "star_touch_action": null,
      "star_exit_sample": null,
      "star_exit_vi": null,
      "star_sample": null,
      "star_vi": null,
      "star_global_timer": null,
      "end_action": 67109952,
      "end_x": -2095.695801,
      "end_y": 2560.0,
      "end_z": -1623.533325,
      "first_walking_sample": 101,
      "first_walking_vi": 292,
      "first_jump_sample": 135,
      "first_jump_vi": 360,
      "first_jump_kick_sample": 106,
      "first_jump_kick_vi": 302,
      "parity_hash": "46ff3db0029a3581",
      "parity_checkpoints": 34,
      "result": "rejected: star not reached"
    },
    {
      "candidate": "launch_suffix_140_dx+0_dy-4",
      "edit_count": 62,
      "csv": "C:\\Users\\sawaiz\\Desktop\\superMario64-TAS\\logs\\run_us_20260722_135918.csv",
      "rows": 342,
      "reached_star": false,
      "star_touch_sample": null,
      "star_touch_vi": null,
      "star_touch_action": null,
      "star_exit_sample": null,
      "star_exit_vi": null,
      "star_sample": null,
      "star_vi": null,
      "star_global_timer": null,
      "end_action": 8651858,
      "end_x": -2073.245117,
      "end_y": 2561.215576,
      "end_z": -1566.251709,
      "first_walking_sample": 101,
      "first_walking_vi": 292,
      "first_jump_sample": 135,
      "first_jump_vi": 360,
      "first_jump_kick_sample": 106,
      "first_jump_kick_vi": 302,
      "parity_hash": "663f8b3b413fe287",
      "parity_checkpoints": 34,
      "result": "rejected: star not reached"
    },
    {
      "candidate": "launch_suffix_140_dx+0_dy+4",
      "edit_count": 62,
      "csv": "C:\\Users\\sawaiz\\Desktop\\superMario64-TAS\\logs\\run_us_20260722_135922.csv",
      "rows": 342,
      "reached_star": false,
      "star_touch_sample": null,
      "star_touch_vi": null,
      "star_touch_action": null,
      "star_exit_sample": null,
      "star_exit_vi": null,
      "star_sample": null,
      "star_vi": null,
      "star_global_timer": null,
      "end_action": 50333838,
      "end_x": -5174.34082,
      "end_y": 447.252075,
      "end_z": 719.809448,
      "first_walking_sample": 101,
      "first_walking_vi": 292,
      "first_jump_sample": 135,
      "first_jump_vi": 360,
      "first_jump_kick_sample": 106,
      "first_jump_kick_vi": 302,
      "parity_hash": "d7827109e5a0318e",
      "parity_checkpoints": 34,
      "result": "rejected: star not reached"
    },
    {
      "candidate": "launch_suffix_143_dx-2_dy+0",
      "edit_count": 59,
      "csv": "C:\\Users\\sawaiz\\Desktop\\superMario64-TAS\\logs\\run_us_20260722_135926.csv",
      "rows": 342,
      "reached_star": false,
      "star_touch_sample": null,
      "star_touch_vi": null,
      "star_touch_action": null,
      "star_exit_sample": null,
      "star_exit_vi": null,
      "star_sample": null,
      "star_vi": null,
      "star_global_timer": null,
      "end_action": 67109952,
      "end_x": -1459.950073,
      "end_y": 2560.0,
      "end_z": -1447.06543,
      "first_walking_sample": 101,
      "first_walking_vi": 292,
      "first_jump_sample": 135,
      "first_jump_vi": 360,
      "first_jump_kick_sample": 106,
      "first_jump_kick_vi": 302,
      "parity_hash": "d1d4f25f78ecbc6c",
      "parity_checkpoints": 34,
      "result": "rejected: star not reached"
    },
    {
      "candidate": "launch_suffix_143_dx+2_dy+0",
      "edit_count": 59,
      "csv": "C:\\Users\\sawaiz\\Desktop\\superMario64-TAS\\logs\\run_us_20260722_135931.csv",
      "rows": 342,
      "reached_star": false,
      "star_touch_sample": null,
      "star_touch_vi": null,
      "star_touch_action": null,
      "star_exit_sample": null,
      "star_exit_vi": null,
      "star_sample": null,
      "star_vi": null,
      "star_global_timer": null,
      "end_action": 67109952,
      "end_x": -2095.046387,
      "end_y": 2560.0,
      "end_z": -1623.385864,
      "first_walking_sample": 101,
      "first_walking_vi": 292,
      "first_jump_sample": 135,
      "first_jump_vi": 360,
      "first_jump_kick_sample": 106,
      "first_jump_kick_vi": 302,
      "parity_hash": "1296186c0f8403cf",
      "parity_checkpoints": 34,
      "result": "rejected: star not reached"
    },
    {
      "candidate": "launch_suffix_143_dx+0_dy-4",
      "edit_count": 59,
      "csv": "C:\\Users\\sawaiz\\Desktop\\superMario64-TAS\\logs\\run_us_20260722_135935.csv",
      "rows": 342,
      "reached_star": false,
      "star_touch_sample": null,
      "star_touch_vi": null,
      "star_touch_action": null,
      "star_exit_sample": null,
      "star_exit_vi": null,
      "star_sample": null,
      "star_vi": null,
      "star_global_timer": null,
      "end_action": 67109952,
      "end_x": -2090.053467,
      "end_y": 2560.0,
      "end_z": -1628.890503,
      "first_walking_sample": 101,
      "first_walking_vi": 292,
      "first_jump_sample": 135,
      "first_jump_vi": 360,
      "first_jump_kick_sample": 106,
      "first_jump_kick_vi": 302,
      "parity_hash": "814fb9e3761e8ba6",
      "parity_checkpoints": 34,
      "result": "rejected: star not reached"
    },
    {
      "candidate": "launch_suffix_143_dx+0_dy+4",
      "edit_count": 59,
      "csv": "C:\\Users\\sawaiz\\Desktop\\superMario64-TAS\\logs\\run_us_20260722_135939.csv",
      "rows": 342,
      "reached_star": false,
      "star_touch_sample": null,
      "star_touch_vi": null,
      "star_touch_action": null,
      "star_exit_sample": null,
      "star_exit_vi": null,
      "star_sample": null,
      "star_vi": null,
      "star_global_timer": null,
      "end_action": 8651858,
      "end_x": -2791.328125,
      "end_y": 2639.342773,
      "end_z": -1080.114746,
      "first_walking_sample": 101,
      "first_walking_vi": 292,
      "first_jump_sample": 135,
      "first_jump_vi": 360,
      "first_jump_kick_sample": 106,
      "first_jump_kick_vi": 302,
      "parity_hash": "bf3f8289e43cb62e",
      "parity_checkpoints": 34,
      "result": "rejected: star not reached"
    },
    {
      "candidate": "launch_suffix_145_dx-2_dy+0",
      "edit_count": 57,
      "csv": "C:\\Users\\sawaiz\\Desktop\\superMario64-TAS\\logs\\run_us_20260722_140239.csv",
      "rows": 342,
      "reached_star": false,
      "star_touch_sample": null,
      "star_touch_vi": null,
      "star_touch_action": null,
      "star_exit_sample": null,
      "star_exit_vi": null,
      "star_sample": null,
      "star_vi": null,
      "star_global_timer": null,
      "end_action": 67109952,
      "end_x": -1453.005859,
      "end_y": 2560.0,
      "end_z": -1445.336182,
      "first_walking_sample": 101,
      "first_walking_vi": 292,
      "first_jump_sample": 135,
      "first_jump_vi": 360,
      "first_jump_kick_sample": 106,
      "first_jump_kick_vi": 302,
      "parity_hash": "6b8a954da56a7465",
      "parity_checkpoints": 34,
      "result": "rejected: star not reached"
    },
    {
      "candidate": "launch_suffix_145_dx+2_dy+0",
      "edit_count": 57,
      "csv": "C:\\Users\\sawaiz\\Desktop\\superMario64-TAS\\logs\\run_us_20260722_140009.csv",
      "rows": 342,
      "reached_star": false,
      "star_touch_sample": null,
      "star_touch_vi": null,
      "star_touch_action": null,
      "star_exit_sample": null,
      "star_exit_vi": null,
      "star_sample": null,
      "star_vi": null,
      "star_global_timer": null,
      "end_action": 8651858,
      "end_x": -2077.014893,
      "end_y": 2563.303955,
      "end_z": -1564.032959,
      "first_walking_sample": 101,
      "first_walking_vi": 292,
      "first_jump_sample": 135,
      "first_jump_vi": 360,
      "first_jump_kick_sample": 106,
      "first_jump_kick_vi": 302,
      "parity_hash": "a478c00747faf06c",
      "parity_checkpoints": 34,
      "result": "rejected: star not reached"
    },
    {
      "candidate": "launch_suffix_145_dx+0_dy-4",
      "edit_count": 57,
      "csv": "C:\\Users\\sawaiz\\Desktop\\superMario64-TAS\\logs\\run_us_20260722_140013.csv",
      "rows": 342,
      "reached_star": true,
      "star_touch_sample": 224,
      "star_touch_vi": 538,
      "star_touch_action": 6404,
      "star_exit_sample": 228,
      "star_exit_vi": 546,
      "star_sample": 228,
      "star_vi": 546,
      "star_global_timer": 2360,
      "end_action": 4866,
      "end_x": -1976.03186,
      "end_y": -2518.0,
      "end_z": -2897.080078,
      "first_walking_sample": 101,
      "first_walking_vi": 292,
      "first_jump_sample": 135,
      "first_jump_vi": 360,
      "first_jump_kick_sample": 106,
      "first_jump_kick_vi": 302,
      "parity_hash": "ce4ac67839bde3b9",
      "parity_checkpoints": 34,
      "result": "ties verified seed"
    },
    {
      "candidate": "launch_suffix_145_dx+0_dy+4",
      "edit_count": 57,
      "csv": "C:\\Users\\sawaiz\\Desktop\\superMario64-TAS\\logs\\run_us_20260722_140017.csv",
      "rows": 342,
      "reached_star": true,
      "star_touch_sample": 224,
      "star_touch_vi": 538,
      "star_touch_action": 6404,
      "star_exit_sample": 228,
      "star_exit_vi": 546,
      "star_sample": 228,
      "star_vi": 546,
      "star_global_timer": 2360,
      "end_action": 4866,
      "end_x": -1976.088501,
      "end_y": -2518.0,
      "end_z": -2897.077637,
      "first_walking_sample": 101,
      "first_walking_vi": 292,
      "first_jump_sample": 135,
      "first_jump_vi": 360,
      "first_jump_kick_sample": 106,
      "first_jump_kick_vi": 302,
      "parity_hash": "1ff58020789b1b76",
      "parity_checkpoints": 34,
      "result": "ties verified seed"
    },
    {
      "candidate": "launch_suffix_147_dx-2_dy+0",
      "edit_count": 55,
      "csv": "C:\\Users\\sawaiz\\Desktop\\superMario64-TAS\\logs\\run_us_20260722_140021.csv",
      "rows": 342,
      "reached_star": false,
      "star_touch_sample": null,
      "star_touch_vi": null,
      "star_touch_action": null,
      "star_exit_sample": null,
      "star_exit_vi": null,
      "star_sample": null,
      "star_vi": null,
      "star_global_timer": null,
      "end_action": 67109952,
      "end_x": -1461.596313,
      "end_y": 2560.0,
      "end_z": -1447.47522,
      "first_walking_sample": 101,
      "first_walking_vi": 292,
      "first_jump_sample": 135,
      "first_jump_vi": 360,
      "first_jump_kick_sample": 106,
      "first_jump_kick_vi": 302,
      "parity_hash": "935030301edaf209",
      "parity_checkpoints": 34,
      "result": "rejected: star not reached"
    },
    {
      "candidate": "launch_suffix_147_dx+2_dy+0",
      "edit_count": 55,
      "csv": "C:\\Users\\sawaiz\\Desktop\\superMario64-TAS\\logs\\run_us_20260722_140026.csv",
      "rows": 342,
      "reached_star": false,
      "star_touch_sample": null,
      "star_touch_vi": null,
      "star_touch_action": null,
      "star_exit_sample": null,
      "star_exit_vi": null,
      "star_sample": null,
      "star_vi": null,
      "star_global_timer": null,
      "end_action": 8651858,
      "end_x": -2076.279541,
      "end_y": 2560.0,
      "end_z": -1617.558716,
      "first_walking_sample": 101,
      "first_walking_vi": 292,
      "first_jump_sample": 135,
      "first_jump_vi": 360,
      "first_jump_kick_sample": 106,
      "first_jump_kick_vi": 302,
      "parity_hash": "20a1302921c7eedf",
      "parity_checkpoints": 34,
      "result": "rejected: star not reached"
    },
    {
      "candidate": "launch_suffix_147_dx+0_dy-4",
      "edit_count": 55,
      "csv": "C:\\Users\\sawaiz\\Desktop\\superMario64-TAS\\logs\\run_us_20260722_140030.csv",
      "rows": 342,
      "reached_star": true,
      "star_touch_sample": 224,
      "star_touch_vi": 538,
      "star_touch_action": 6404,
      "star_exit_sample": 228,
      "star_exit_vi": 546,
      "star_sample": 228,
      "star_vi": 546,
      "star_global_timer": 2360,
      "end_action": 4866,
      "end_x": -1976.03186,
      "end_y": -2518.0,
      "end_z": -2897.080078,
      "first_walking_sample": 101,
      "first_walking_vi": 292,
      "first_jump_sample": 135,
      "first_jump_vi": 360,
      "first_jump_kick_sample": 106,
      "first_jump_kick_vi": 302,
      "parity_hash": "ce4ac67839bde3b9",
      "parity_checkpoints": 34,
      "result": "ties verified seed"
    },
    {
      "candidate": "launch_suffix_147_dx+0_dy+4",
      "edit_count": 55,
      "csv": "C:\\Users\\sawaiz\\Desktop\\superMario64-TAS\\logs\\run_us_20260722_140035.csv",
      "rows": 342,
      "reached_star": true,
      "star_touch_sample": 224,
      "star_touch_vi": 538,
      "star_touch_action": 6404,
      "star_exit_sample": 228,
      "star_exit_vi": 546,
      "star_sample": 228,
      "star_vi": 546,
      "star_global_timer": 2360,
      "end_action": 4866,
      "end_x": -1976.045776,
      "end_y": -2518.0,
      "end_z": -2897.07959,
      "first_walking_sample": 101,
      "first_walking_vi": 292,
      "first_jump_sample": 135,
      "first_jump_vi": 360,
      "first_jump_kick_sample": 106,
      "first_jump_kick_vi": 302,
      "parity_hash": "b7f97012a0960fbe",
      "parity_checkpoints": 34,
      "result": "ties verified seed"
    },
    {
      "candidate": "runup_1_dx-4_dy+0",
      "edit_count": 59,
      "csv": "C:\\Users\\sawaiz\\Desktop\\superMario64-TAS\\logs\\run_us_20260722_140039.csv",
      "rows": 342,
      "reached_star": false,
      "star_touch_sample": null,
      "star_touch_vi": null,
      "star_touch_action": null,
      "star_exit_sample": null,
      "star_exit_vi": null,
      "star_sample": null,
      "star_vi": null,
      "star_global_timer": null,
      "end_action": 67109952,
      "end_x": -2177.569092,
      "end_y": 2560.0,
      "end_z": -1789.00415,
      "first_walking_sample": 101,
      "first_walking_vi": 292,
      "first_jump_sample": 135,
      "first_jump_vi": 360,
      "first_jump_kick_sample": 106,
      "first_jump_kick_vi": 302,
      "parity_hash": "218071d7fd3cea0e",
      "parity_checkpoints": 34,
      "result": "rejected: star not reached"
    },
    {
      "candidate": "runup_1_dx-2_dy+0",
      "edit_count": 59,
      "csv": "C:\\Users\\sawaiz\\Desktop\\superMario64-TAS\\logs\\run_us_20260722_140043.csv",
      "rows": 342,
      "reached_star": false,
      "star_touch_sample": null,
      "star_touch_vi": null,
      "star_touch_action": null,
      "star_exit_sample": null,
      "star_exit_vi": null,
      "star_sample": null,
      "star_vi": null,
      "star_global_timer": null,
      "end_action": 67109952,
      "end_x": -1962.432617,
      "end_y": 2560.0,
      "end_z": -1569.067993,
      "first_walking_sample": 101,
      "first_walking_vi": 292,
      "first_jump_sample": 135,
      "first_jump_vi": 360,
      "first_jump_kick_sample": 106,
      "first_jump_kick_vi": 302,
      "parity_hash": "93cf2a7d2086b7da",
      "parity_checkpoints": 34,
      "result": "rejected: star not reached"
    },
    {
      "candidate": "runup_1_dx+2_dy+0",
      "edit_count": 59,
      "csv": "C:\\Users\\sawaiz\\Desktop\\superMario64-TAS\\logs\\run_us_20260722_140047.csv",
      "rows": 342,
      "reached_star": false,
      "star_touch_sample": null,
      "star_touch_vi": null,
      "star_touch_action": null,
      "star_exit_sample": null,
      "star_exit_vi": null,
      "star_sample": null,
      "star_vi": null,
      "star_global_timer": null,
      "end_action": 67109952,
      "end_x": -2115.800293,
      "end_y": 2560.0,
      "end_z": -1616.089844,
      "first_walking_sample": 101,
      "first_walking_vi": 292,
      "first_jump_sample": 135,
      "first_jump_vi": 360,
      "first_jump_kick_sample": 106,
      "first_jump_kick_vi": 302,
      "parity_hash": "bfa8e32fd87c3abe",
      "parity_checkpoints": 34,
      "result": "rejected: star not reached"
    },
    {
      "candidate": "runup_1_dx+4_dy+0",
      "edit_count": 59,
      "csv": "C:\\Users\\sawaiz\\Desktop\\superMario64-TAS\\logs\\run_us_20260722_140052.csv",
      "rows": 342,
      "reached_star": false,
      "star_touch_sample": null,
      "star_touch_vi": null,
      "star_touch_action": null,
      "star_exit_sample": null,
      "star_exit_vi": null,
      "star_sample": null,
      "star_vi": null,
      "star_global_timer": null,
      "end_action": 67109952,
      "end_x": -2136.75415,
      "end_y": 2563.928223,
      "end_z": -1602.49292,
      "first_walking_sample": 101,
      "first_walking_vi": 292,
      "first_jump_sample": 135,
      "first_jump_vi": 360,
      "first_jump_kick_sample": 106,
      "first_jump_kick_vi": 302,
      "parity_hash": "13cbbfd73da02cc3",
      "parity_checkpoints": 34,
      "result": "rejected: star not reached"
    },
    {
      "candidate": "runup_1_dx+0_dy-3",
      "edit_count": 59,
      "csv": "C:\\Users\\sawaiz\\Desktop\\superMario64-TAS\\logs\\run_us_20260722_140056.csv",
      "rows": 342,
      "reached_star": false,
      "star_touch_sample": null,
      "star_touch_vi": null,
      "star_touch_action": null,
      "star_exit_sample": null,
      "star_exit_vi": null,
      "star_sample": null,
      "star_vi": null,
      "star_global_timer": null,
      "end_action": 67109952,
      "end_x": -2095.033203,
      "end_y": 2560.0,
      "end_z": -1623.382568,
      "first_walking_sample": 101,
      "first_walking_vi": 292,
      "first_jump_sample": 135,
      "first_jump_vi": 360,
      "first_jump_kick_sample": 106,
      "first_jump_kick_vi": 302,
      "parity_hash": "3ac09f2f5157bf50",
      "parity_checkpoints": 34,
      "result": "rejected: star not reached"
    },
    {
      "candidate": "runup_2_dx-4_dy+0",
      "edit_count": 80,
      "csv": "C:\\Users\\sawaiz\\Desktop\\superMario64-TAS\\logs\\run_us_20260722_140100.csv",
      "rows": 342,
      "reached_star": false,
      "star_touch_sample": null,
      "star_touch_vi": null,
      "star_touch_action": null,
      "star_exit_sample": null,
      "star_exit_vi": null,
      "star_sample": null,
      "star_vi": null,
      "star_global_timer": null,
      "end_action": 8651858,
      "end_x": -2958.419678,
      "end_y": 2219.80957,
      "end_z": -744.072815,
      "first_walking_sample": 101,
      "first_walking_vi": 292,
      "first_jump_sample": 135,
      "first_jump_vi": 360,
      "first_jump_kick_sample": 106,
      "first_jump_kick_vi": 302,
      "parity_hash": "9bf02ede6a34b07d",
      "parity_checkpoints": 34,
      "result": "rejected: star not reached"
    },
    {
      "candidate": "runup_2_dx-2_dy+0",
      "edit_count": 80,
      "csv": "C:\\Users\\sawaiz\\Desktop\\superMario64-TAS\\logs\\run_us_20260722_140105.csv",
      "rows": 342,
      "reached_star": false,
      "star_touch_sample": null,
      "star_touch_vi": null,
      "star_touch_action": null,
      "star_exit_sample": null,
      "star_exit_vi": null,
      "star_sample": null,
      "star_vi": null,
      "star_global_timer": null,
      "end_action": 8651858,
      "end_x": -2791.173828,
      "end_y": 2674.816162,
      "end_z": -1141.955933,
      "first_walking_sample": 101,
      "first_walking_vi": 292,
      "first_jump_sample": 135,
      "first_jump_vi": 360,
      "first_jump_kick_sample": 106,
      "first_jump_kick_vi": 302,
      "parity_hash": "dd641cd43051afb9",
      "parity_checkpoints": 34,
      "result": "rejected: star not reached"
    },
    {
      "candidate": "runup_2_dx+2_dy+0",
      "edit_count": 80,
      "csv": "C:\\Users\\sawaiz\\Desktop\\superMario64-TAS\\logs\\run_us_20260722_140109.csv",
      "rows": 342,
      "reached_star": false,
      "star_touch_sample": null,
      "star_touch_vi": null,
      "star_touch_action": null,
      "star_exit_sample": null,
      "star_exit_vi": null,
      "star_sample": null,
      "star_vi": null,
      "star_global_timer": null,
      "end_action": 67109952,
      "end_x": -2095.095947,
      "end_y": 2560.0,
      "end_z": -1623.398315,
      "first_walking_sample": 101,
      "first_walking_vi": 292,
      "first_jump_sample": 135,
      "first_jump_vi": 360,
      "first_jump_kick_sample": 106,
      "first_jump_kick_vi": 302,
      "parity_hash": "2e40ffb7088c88cd",
      "parity_checkpoints": 34,
      "result": "rejected: star not reached"
    },
    {
      "candidate": "runup_2_dx+4_dy+0",
      "edit_count": 80,
      "csv": "C:\\Users\\sawaiz\\Desktop\\superMario64-TAS\\logs\\run_us_20260722_140113.csv",
      "rows": 342,
      "reached_star": false,
      "star_touch_sample": null,
      "star_touch_vi": null,
      "star_touch_action": null,
      "star_exit_sample": null,
      "star_exit_vi": null,
      "star_sample": null,
      "star_vi": null,
      "star_global_timer": null,
      "end_action": 67109952,
      "end_x": -2094.881592,
      "end_y": 2560.0,
      "end_z": -1623.63208,
      "first_walking_sample": 101,
      "first_walking_vi": 292,
      "first_jump_sample": 135,
      "first_jump_vi": 360,
      "first_jump_kick_sample": 106,
      "first_jump_kick_vi": 302,
      "parity_hash": "70bc2b694b776726",
      "parity_checkpoints": 34,
      "result": "rejected: star not reached"
    },
    {
      "candidate": "runup_2_dx+0_dy-3",
      "edit_count": 80,
      "csv": "C:\\Users\\sawaiz\\Desktop\\superMario64-TAS\\logs\\run_us_20260722_140118.csv",
      "rows": 342,
      "reached_star": false,
      "star_touch_sample": null,
      "star_touch_vi": null,
      "star_touch_action": null,
      "star_exit_sample": null,
      "star_exit_vi": null,
      "star_sample": null,
      "star_vi": null,
      "star_global_timer": null,
      "end_action": 67109952,
      "end_x": -2095.485352,
      "end_y": 2560.0,
      "end_z": -1623.489624,
      "first_walking_sample": 101,
      "first_walking_vi": 292,
      "first_jump_sample": 135,
      "first_jump_vi": 360,
      "first_jump_kick_sample": 106,
      "first_jump_kick_vi": 302,
      "parity_hash": "9bd16a8634c3ef11",
      "parity_checkpoints": 34,
      "result": "rejected: star not reached"
    },
    {
      "candidate": "kick_105_-1",
      "edit_count": 55,
      "csv": "C:\\Users\\sawaiz\\Desktop\\superMario64-TAS\\logs\\run_us_20260722_140123.csv",
      "rows": 342,
      "reached_star": false,
      "star_touch_sample": null,
      "star_touch_vi": null,
      "star_touch_action": null,
      "star_exit_sample": null,
      "star_exit_vi": null,
      "star_sample": null,
      "star_vi": null,
      "star_global_timer": null,
      "end_action": 67109952,
      "end_x": -2186.962891,
      "end_y": 2594.498047,
      "end_z": -1567.823975,
      "first_walking_sample": 101,
      "first_walking_vi": 292,
      "first_jump_sample": 135,
      "first_jump_vi": 360,
      "first_jump_kick_sample": 105,
      "first_jump_kick_vi": 300,
      "parity_hash": "25cb059c1e7fcc21",
      "parity_checkpoints": 34,
      "result": "rejected: star not reached"
    },
    {
      "candidate": "kick_105_+1",
      "edit_count": 55,
      "csv": "C:\\Users\\sawaiz\\Desktop\\superMario64-TAS\\logs\\run_us_20260722_140127.csv",
      "rows": 342,
      "reached_star": false,
      "star_touch_sample": null,
      "star_touch_vi": null,
      "star_touch_action": null,
      "star_exit_sample": null,
      "star_exit_vi": null,
      "star_sample": null,
      "star_vi": null,
      "star_global_timer": null,
      "end_action": 9176147,
      "end_x": -2208.341797,
      "end_y": 2560.0,
      "end_z": -2225.216797,
      "first_walking_sample": 101,
      "first_walking_vi": 292,
      "first_jump_sample": null,
      "first_jump_vi": null,
      "first_jump_kick_sample": null,
      "first_jump_kick_vi": null,
      "parity_hash": "fe42a583827c6d71",
      "parity_checkpoints": 34,
      "result": "rejected: star not reached"
    },
    {
      "candidate": "kick_119_-1",
      "edit_count": 55,
      "csv": "C:\\Users\\sawaiz\\Desktop\\superMario64-TAS\\logs\\run_us_20260722_140132.csv",
      "rows": 342,
      "reached_star": false,
      "star_touch_sample": null,
      "star_touch_vi": null,
      "star_touch_action": null,
      "star_exit_sample": null,
      "star_exit_vi": null,
      "star_sample": null,
      "star_vi": null,
      "star_global_timer": null,
      "end_action": 67109952,
      "end_x": -2272.439941,
      "end_y": 2650.117676,
      "end_z": -1500.712158,
      "first_walking_sample": 101,
      "first_walking_vi": 292,
      "first_jump_sample": null,
      "first_jump_vi": null,
      "first_jump_kick_sample": 106,
      "first_jump_kick_vi": 302,
      "parity_hash": "eed6c8ebef78aa4a",
      "parity_checkpoints": 34,
      "result": "rejected: star not reached"
    },
    {
      "candidate": "kick_119_+1",
      "edit_count": 55,
      "csv": "C:\\Users\\sawaiz\\Desktop\\superMario64-TAS\\logs\\run_us_20260722_140136.csv",
      "rows": 342,
      "reached_star": false,
      "star_touch_sample": null,
      "star_touch_vi": null,
      "star_touch_action": null,
      "star_exit_sample": null,
      "star_exit_vi": null,
      "star_sample": null,
      "star_vi": null,
      "star_global_timer": null,
      "end_action": 67109952,
      "end_x": -2272.439941,
      "end_y": 2650.117676,
      "end_z": -1500.712158,
      "first_walking_sample": 101,
      "first_walking_vi": 292,
      "first_jump_sample": null,
      "first_jump_vi": null,
      "first_jump_kick_sample": 106,
      "first_jump_kick_vi": 302,
      "parity_hash": "93667001f0a1b8db",
      "parity_checkpoints": 34,
      "result": "rejected: star not reached"
    },
    {
      "candidate": "jump_134_-1",
      "edit_count": 55,
      "csv": "C:\\Users\\sawaiz\\Desktop\\superMario64-TAS\\logs\\run_us_20260722_140140.csv",
      "rows": 342,
      "reached_star": false,
      "star_touch_sample": null,
      "star_touch_vi": null,
      "star_touch_action": null,
      "star_exit_sample": null,
      "star_exit_vi": null,
      "star_sample": null,
      "star_vi": null,
      "star_global_timer": null,
      "end_action": 8651858,
      "end_x": -2853.036621,
      "end_y": 2493.324219,
      "end_z": -972.486328,
      "first_walking_sample": 101,
      "first_walking_vi": 292,
      "first_jump_sample": null,
      "first_jump_vi": null,
      "first_jump_kick_sample": 106,
      "first_jump_kick_vi": 302,
      "parity_hash": "3c1026017c31e107",
      "parity_checkpoints": 34,
      "result": "rejected: star not reached"
    },
    {
      "candidate": "jump_134_+1",
      "edit_count": 55,
      "csv": "C:\\Users\\sawaiz\\Desktop\\superMario64-TAS\\logs\\run_us_20260722_140145.csv",
      "rows": 342,
      "reached_star": false,
      "star_touch_sample": null,
      "star_touch_vi": null,
      "star_touch_action": null,
      "star_exit_sample": null,
      "star_exit_vi": null,
      "star_sample": null,
      "star_vi": null,
      "star_global_timer": null,
      "end_action": 67109952,
      "end_x": -2136.282471,
      "end_y": 2563.928223,
      "end_z": -1602.673462,
      "first_walking_sample": 101,
      "first_walking_vi": 292,
      "first_jump_sample": 136,
      "first_jump_vi": 362,
      "first_jump_kick_sample": 106,
      "first_jump_kick_vi": 302,
      "parity_hash": "05dd2e65b88e985d",
      "parity_checkpoints": 34,
      "result": "rejected: star not reached"
    },
    {
      "candidate": "kicks_-1_-1",
      "edit_count": 57,
      "csv": "C:\\Users\\sawaiz\\Desktop\\superMario64-TAS\\logs\\run_us_20260722_140149.csv",
      "rows": 342,
      "reached_star": false,
      "star_touch_sample": null,
      "star_touch_vi": null,
      "star_touch_action": null,
      "star_exit_sample": null,
      "star_exit_vi": null,
      "star_sample": null,
      "star_vi": null,
      "star_global_timer": null,
      "end_action": 50333838,
      "end_x": -5058.646973,
      "end_y": 537.721069,
      "end_z": 592.101562,
      "first_walking_sample": 101,
      "first_walking_vi": 292,
      "first_jump_sample": 135,
      "first_jump_vi": 360,
      "first_jump_kick_sample": 105,
      "first_jump_kick_vi": 300,
      "parity_hash": "0a2a0aa374a6342a",
      "parity_checkpoints": 34,
      "result": "rejected: star not reached"
    },
    {
      "candidate": "kicks_-1_+1",
      "edit_count": 57,
      "csv": "C:\\Users\\sawaiz\\Desktop\\superMario64-TAS\\logs\\run_us_20260722_140154.csv",
      "rows": 342,
      "reached_star": false,
      "star_touch_sample": null,
      "star_touch_vi": null,
      "star_touch_action": null,
      "star_exit_sample": null,
      "star_exit_vi": null,
      "star_sample": null,
      "star_vi": null,
      "star_global_timer": null,
      "end_action": 67109952,
      "end_x": -2273.253418,
      "end_y": 2650.416016,
      "end_z": -1500.601074,
      "first_walking_sample": 101,
      "first_walking_vi": 292,
      "first_jump_sample": null,
      "first_jump_vi": null,
      "first_jump_kick_sample": 105,
      "first_jump_kick_vi": 300,
      "parity_hash": "c46ea561037791ce",
      "parity_checkpoints": 34,
      "result": "rejected: star not reached"
    },
    {
      "candidate": "kicks_+1_-1",
      "edit_count": 57,
      "csv": "C:\\Users\\sawaiz\\Desktop\\superMario64-TAS\\logs\\run_us_20260722_140158.csv",
      "rows": 342,
      "reached_star": false,
      "star_touch_sample": null,
      "star_touch_vi": null,
      "star_touch_action": null,
      "star_exit_sample": null,
      "star_exit_vi": null,
      "star_sample": null,
      "star_vi": null,
      "star_global_timer": null,
      "end_action": 902,
      "end_x": -2119.720459,
      "end_y": 2560.0,
      "end_z": -2400.492432,
      "first_walking_sample": 101,
      "first_walking_vi": 292,
      "first_jump_sample": null,
      "first_jump_vi": null,
      "first_jump_kick_sample": null,
      "first_jump_kick_vi": null,
      "parity_hash": "2fa2f839d3f057ea",
      "parity_checkpoints": 34,
      "result": "rejected: star not reached"
    },
    {
      "candidate": "kicks_+1_+1",
      "edit_count": 57,
      "csv": "C:\\Users\\sawaiz\\Desktop\\superMario64-TAS\\logs\\run_us_20260722_140203.csv",
      "rows": 342,
      "reached_star": false,
      "star_touch_sample": null,
      "star_touch_vi": null,
      "star_touch_action": null,
      "star_exit_sample": null,
      "star_exit_vi": null,
      "star_sample": null,
      "star_vi": null,
      "star_global_timer": null,
      "end_action": 9176147,
      "end_x": -2267.816162,
      "end_y": 2560.0,
      "end_z": -2076.262451,
      "first_walking_sample": 101,
      "first_walking_vi": 292,
      "first_jump_sample": null,
      "first_jump_vi": null,
      "first_jump_kick_sample": null,
      "first_jump_kick_vi": null,
      "parity_hash": "0c925bc8898206e3",
      "parity_checkpoints": 34,
      "result": "rejected: star not reached"
    }
  ]
}
